structured/__init__.py
structured/base_types.py
structured/py.typed
structured/structured.py
structured/type_checking.py
structured/utils.py
structured/hint_types/__init__.py
structured/hint_types/arrays.py
structured/hint_types/basic_types.py
structured/hint_types/condition.py
structured/hint_types/serialize_as.py
structured/hint_types/strings.py
structured/hint_types/tuples.py
structured/serializers/__init__.py
structured/serializers/api.py
structured/serializers/arrays.py
structured/serializers/conditional.py
structured/serializers/self.py
structured/serializers/strings.py
structured/serializers/structs.py
structured/serializers/structured.py
structured/serializers/tuples.py
structured/serializers/unions.py
structured_classes-3.1.0.dist-info/LICENSE
structured_classes-3.1.0.dist-info/METADATA
structured_classes-3.1.0.dist-info/WHEEL
structured_classes-3.1.0.dist-info/top_level.txt
structured_classes-3.1.0.dist-info/RECORD
