Metadata-Version: 2.1
Name: structured_classes
Version: 3.1.0
Summary: Annotated classes that pack and unpack C structures.
Author: lojack5
License: BSD 3-Clause
Project-URL: Homepage, https://github.com/lojack5/structured
Project-URL: Bug Tracker, https://github.com/lojack5/structured/issues
Classifier: Intended Audience :: Developers
Classifier: Programming Language :: Python :: 3 :: Only
Classifier: Programming Language :: Python :: 3.9
Classifier: Programming Language :: Python :: 3.10
Classifier: Programming Language :: Python :: 3.11
Classifier: Programming Language :: Python :: 3.12
Classifier: License :: OSI Approved :: BSD License
Classifier: Operating System :: OS Independent
Classifier: Typing :: Typed
Requires-Python: >=3.9
License-File: LICENSE
Requires-Dist: typing-extensions ~=4.4.0 ; python_version < "3.11"
